dh/__init__.py
dh/audio/__init__.py
dh/data/__init__.py
dh/data/colormaps/accent.json
dh/data/colormaps/afmhot.json
dh/data/colormaps/autumn.json
dh/data/colormaps/binary.json
dh/data/colormaps/blues.json
dh/data/colormaps/bone.json
dh/data/colormaps/brbg.json
dh/data/colormaps/brg.json
dh/data/colormaps/bugn.json
dh/data/colormaps/bupu.json
dh/data/colormaps/bwr.json
dh/data/colormaps/cmrmap.json
dh/data/colormaps/cool.json
dh/data/colormaps/coolwarm.json
dh/data/colormaps/copper.json
dh/data/colormaps/cubehelix.json
dh/data/colormaps/dark2.json
dh/data/colormaps/flag.json
dh/data/colormaps/gist_earth.json
dh/data/colormaps/gist_gray.json
dh/data/colormaps/gist_heat.json
dh/data/colormaps/gist_ncar.json
dh/data/colormaps/gist_rainbow.json
dh/data/colormaps/gist_stern.json
dh/data/colormaps/gist_yarg.json
dh/data/colormaps/gnbu.json
dh/data/colormaps/gnuplot.json
dh/data/colormaps/gnuplot2.json
dh/data/colormaps/gray.json
dh/data/colormaps/greens.json
dh/data/colormaps/greys.json
dh/data/colormaps/hot.json
dh/data/colormaps/hsv.json
dh/data/colormaps/inferno.json
dh/data/colormaps/jet.json
dh/data/colormaps/magma.json
dh/data/colormaps/nipy_spectral.json
dh/data/colormaps/ocean.json
dh/data/colormaps/oranges.json
dh/data/colormaps/orrd.json
dh/data/colormaps/paired.json
dh/data/colormaps/pastel1.json
dh/data/colormaps/pastel2.json
dh/data/colormaps/pink.json
dh/data/colormaps/piyg.json
dh/data/colormaps/plasma.json
dh/data/colormaps/plot.json
dh/data/colormaps/plot2.json
dh/data/colormaps/prgn.json
dh/data/colormaps/prism.json
dh/data/colormaps/pubu.json
dh/data/colormaps/pubugn.json
dh/data/colormaps/puor.json
dh/data/colormaps/purd.json
dh/data/colormaps/purples.json
dh/data/colormaps/rainbow.json
dh/data/colormaps/rdbu.json
dh/data/colormaps/rdgy.json
dh/data/colormaps/rdpu.json
dh/data/colormaps/rdylbu.json
dh/data/colormaps/rdylgn.json
dh/data/colormaps/reds.json
dh/data/colormaps/seismic.json
dh/data/colormaps/set1.json
dh/data/colormaps/set2.json
dh-0.15.3.dist-info/LICENSE.txt
dh-0.15.3.dist-info/METADATA
dh-0.15.3.dist-info/WHEEL
dh-0.15.3.dist-info/top_level.txt
dh-0.15.3.dist-info/RECORD
