Metadata-Version: 2.1
Name: dh
Version: 0.15.3
Summary: Personal Python package of Daniel Haase
Home-page: https://github.com/dhaase-de/dh-python-dh
Author: Daniel Haase
License: UNKNOWN
Platform: UNKNOWN
Classifier: Development Status :: 4 - Beta
Classifier: License :: OSI Approved :: MIT License
Classifier: Programming Language :: Python :: 3
Classifier: Operating System :: OS Independent
Classifier: Topic :: Utilities
License-File: LICENSE.txt
